tor_util/__init__.py
tor_util/tor_util_qrc.py
tor_util-0.1.3.data/data/share/applications/tor_util.desktop
tor_util-0.1.3.data/data/share/bash-completion/completions/tor_util_cli.py
tor_util-0.1.3.data/data/share/icons/hicolor/128x128/apps/tor-util.png
tor_util-0.1.3.data/data/share/icons/hicolor/256x256/apps/tor-util.png
tor_util-0.1.3.data/data/share/icons/hicolor/32x32/apps/tor-util.png
tor_util-0.1.3.data/data/share/icons/hicolor/48x48/apps/tor-util.png
tor_util-0.1.3.data/data/share/icons/hicolor/512x512/apps/tor-util.png
tor_util-0.1.3.data/data/share/icons/hicolor/64x64/apps/tor-util.png
tor_util-0.1.3.data/data/share/icons/hicolor/72x72/apps/tor-util.png
tor_util-0.1.3.data/data/share/icons/hicolor/96x96/apps/tor-util.png
tor_util-0.1.3.data/data/share/tor-util/tor_util.ui
tor_util-0.1.3.data/scripts/tor_util_cli.py
tor_util-0.1.3.data/scripts/tor_util_gui.py
tor_util-0.1.3.dist-info/LICENSE
tor_util-0.1.3.dist-info/METADATA
tor_util-0.1.3.dist-info/WHEEL
tor_util-0.1.3.dist-info/top_level.txt
tor_util-0.1.3.dist-info/RECORD
