Metadata-Version: 2.1
Name: tor-util
Version: 0.1.3
Summary: Utility for controling TOR via the API
Home-page: https://github.com/GIJack/tor-util
Author: GI Jack
Author-email: GI_Jack@hackermail.com
License: GPLv3
Classifier: Development Status :: 3 - Alpha 
Classifier: Environment :: Console
Classifier: Environment :: X11 Applications :: Qt
Classifier: Intended Audience :: End Users/Desktop
Classifier: Operating System :: POSIX :: Linux
Classifier: Operating System :: POSIX :: BSD :: FreeBSD
Classifier: Operating System :: POSIX :: BSD :: OpenBSD
Classifier: Operating System :: POSIX
Classifier: Programming Language :: Python
Classifier: Topic :: Utilities
Classifier: Topic :: System :: Networking
License-File: LICENSE
Requires-Dist: PyQt5
Requires-Dist: stem
